zenoh_ros_type/__init__.py
zenoh_ros_type/action.py
zenoh_ros_type/service.py
zenoh_ros_type/autoware_adapi_msgs/__init__.py
zenoh_ros_type/autoware_adapi_msgs/autoware_adapi_v1_msgs.py
zenoh_ros_type/autoware_auto_msgs/__init__.py
zenoh_ros_type/autoware_auto_msgs/autoware_auto_control_msgs.py
zenoh_ros_type/autoware_auto_msgs/autoware_auto_vehicle_msgs.py
zenoh_ros_type/autoware_msgs/__init__.py
zenoh_ros_type/autoware_msgs/autoware_control_msgs.py
zenoh_ros_type/common_interfaces/__init__.py
zenoh_ros_type/common_interfaces/geometry_msgs.py
zenoh_ros_type/common_interfaces/sensor_msgs.py
zenoh_ros_type/common_interfaces/std_msgs.py
zenoh_ros_type/example_interfaces/__init__.py
zenoh_ros_type/example_interfaces/action.py
zenoh_ros_type/example_interfaces/srv.py
zenoh_ros_type/examples/action_client.py
zenoh_ros_type/examples/action_server.py
zenoh_ros_type/examples/listener.py
zenoh_ros_type/examples/service_client.py
zenoh_ros_type/examples/service_server.py
zenoh_ros_type/examples/talker.py
zenoh_ros_type/geographic_info/__init__.py
zenoh_ros_type/geographic_info/geographic_msgs.py
zenoh_ros_type/rcl_interfaces/__init__.py
zenoh_ros_type/rcl_interfaces/action_msgs.py
zenoh_ros_type/rcl_interfaces/builtin_interfaces.py
zenoh_ros_type/rcl_interfaces/rosgraph_msgs.py
zenoh_ros_type/tier4_autoware_msgs/__init__.py
zenoh_ros_type/tier4_autoware_msgs/tier4_control_msgs.py
zenoh_ros_type/tier4_autoware_msgs/tier4_external_api_msgs.py
zenoh_ros_type/unique_identifier_msgs/__init__.py
zenoh_ros_type/unique_identifier_msgs/unique_identifier_msgs.py
zenoh_ros_type-0.2.5.dist-info/METADATA
zenoh_ros_type-0.2.5.dist-info/WHEEL
zenoh_ros_type-0.2.5.dist-info/top_level.txt
zenoh_ros_type-0.2.5.dist-info/RECORD
