Metadata-Version: 2.4
Name: zenoh-ros-type
Version: 0.2.5
Summary: Common class for ROS 2 message used by Zenoh
Author-email: ChenYing Kuo <evshary@gmail.com>
License: Apache-2.0
Project-URL: repository, https://github.com/evshary/zenoh-ros-type-python
Project-URL: Issues, https://github.com/evshary/zenoh-ros-type-python/issues
Requires-Python: >=3.8
Requires-Dist: pycdr2<2.0,>=1.0
Provides-Extra: dev
Requires-Dist: eclipse-zenoh<2.0,>=1.7.1; extra == "dev"
